asterisktask/AppConfig.json.attpl
asterisktask/__init__.py
asterisktask/atnewapp.py
asterisktask/main.py
asterisktask/run.py.attpl
asterisktask/setting.py.attpl
asterisktask/setup.py.attpl
asterisktask/tasks.py.attpl
asterisktask/api/__init__.py
asterisktask/api/http.py
asterisktask/error/__init__.py
asterisktask/error/api.py
asterisktask/error/util.py
asterisktask/lib/__init__.py
asterisktask/lib/nn.py
asterisktask/lib/orm.py
asterisktask/lib/task.py
asterisktask/lib/taskcontrol.py
asterisktask/setup/__init__.py
asterisktask/setup/asterisk.json
asterisktask/setup/log.config
asterisktask/setup/logo.attpl
asterisktask/setup/setting.py
asterisktask/setup/title.attpl
asterisktask/util/__init__.py
asterisktask/util/time.py
asterisktask/util/tool.py
asterisk_task-2.2.0.1226.1518.dist-info/LICENSE
asterisk_task-2.2.0.1226.1518.dist-info/METADATA
asterisk_task-2.2.0.1226.1518.dist-info/WHEEL
asterisk_task-2.2.0.1226.1518.dist-info/entry_points.txt
asterisk_task-2.2.0.1226.1518.dist-info/top_level.txt
asterisk_task-2.2.0.1226.1518.dist-info/RECORD
