Metadata-Version: 2.1
Name: asterisk-task
Version: 2.2.0.1226.1518
Summary: Task management system.
Author: Shan,Tian
Author-email: geoshan@163.com
License: Apache License 2.0
Keywords: task,scheduled task
Platform: Independent
Classifier: Development Status :: 3 - Alpha
Classifier: Topic :: Utilities
Classifier: License :: OSI Approved :: Apache Software License
Classifier: Environment :: Console
Classifier: Intended Audience :: Developers
Classifier: Operating System :: OS Independent
Classifier: Programming Language :: Python :: 3 :: Only
Classifier: Programming Language :: Python :: 3.10
Requires-Python: >=3.10.0
License-File: LICENSE
Requires-Dist: requests>=2.31.0
Requires-Dist: colorama>=0.4.4
Requires-Dist: prettytable>=3.1
Requires-Dist: schedule>=1.1.0
Requires-Dist: Deprecated>=1.2.13
Requires-Dist: asterisk-utils>=0.1.0
Requires-Dist: sqlalchemy>=2.0.36
